modular_torch
