Metadata-Version: 2.1
Name: ModularTorch
Version: 0.1.3
Summary: custom torch wrapper
Home-page: https://github.com/sirreajohn/ModularTorch
Download-URL: https://github.com/sirreajohn/ModularTorch/archive/refs/tags/v0.1a.tar.gz
Author: Mahesh Patapalli
Author-email: mahesh.patapali@gmail.com
License: MIT
Keywords: pytorch,python,deep learning
Classifier: Development Status :: 4 - Beta
Classifier: Intended Audience :: Developers
Classifier: Topic :: Software Development :: Build Tools
Classifier: License :: OSI Approved :: MIT License
Classifier: Programming Language :: Python :: 3
Classifier: Programming Language :: Python :: 3.4
Classifier: Programming Language :: Python :: 3.5
Classifier: Programming Language :: Python :: 3.6
Classifier: Programming Language :: Python :: 3.7
Classifier: Programming Language :: Python :: 3.8
Classifier: Programming Language :: Python :: 3.9
Classifier: Programming Language :: Python :: 3.10
Classifier: Programming Language :: Python :: 3.11
License-File: LICENSE
